m9lib/__init__.py
m9lib/u_args.py
m9lib/u_color.py
m9lib/u_command.py
m9lib/u_control.py
m9lib/u_csv.py
m9lib/u_dictionary.py
m9lib/u_failures.py
m9lib/u_folder.py
m9lib/u_format.py
m9lib/u_logger.py
m9lib/u_scan.py
m9lib/u_timer.py
m9lib/u_type.py
m9lib/u_web.py
m9lib-1.0.0.dist-info/licenses/LICENSE
m9lib-1.0.0.dist-info/METADATA
m9lib-1.0.0.dist-info/WHEEL
m9lib-1.0.0.dist-info/top_level.txt
m9lib-1.0.0.dist-info/RECORD
