Metadata-Version: 2.4
Name: m9lib
Version: 1.0.0
Summary: m9 utility library
Author: M. Fairbanks
Author-email: marcusnyne@gmail.com
License-Expression: Apache-2.0
Project-URL: Homepage, https://github.com/MarcusNyne/m9lib
Keywords: INI,configuration,config,parse,load,batch,etl,logging,color,folder,files,rules,csv
Classifier: Programming Language :: Python :: 3
Classifier: Operating System :: OS Independent
Requires-Python: >=3.10.6
License-File: LICENSE
Requires-Dist: m9ini
Requires-Dist: urllib3
Requires-Dist: beautifulsoup4>=4.12.2
Provides-Extra: dev
Dynamic: license-file
